coretests/__init__.py
coretests/coretests.py
nanamilang/__init__.py
nanamilang/ast.py
nanamilang/bdb.py
nanamilang/builtin.py
nanamilang/destruct.py
nanamilang/fn.py
nanamilang/loader.py
nanamilang/module.py
nanamilang/shortcuts.py
nanamilang/spec.py
nanamilang/token.py
nanamilang/tokenizer.py
nanamilang/contrib/__init__.py
nanamilang/contrib/window.py
nanamilang/datatypes/__init__.py
nanamilang/datatypes/_exports.py
nanamilang/datatypes/_imdict.py
nanamilang/datatypes/atom.py
nanamilang/datatypes/base.py
nanamilang/datatypes/boolean.py
nanamilang/datatypes/callable.py
nanamilang/datatypes/character.py
nanamilang/datatypes/collection.py
nanamilang/datatypes/date.py
nanamilang/datatypes/floatnumber.py
nanamilang/datatypes/function.py
nanamilang/datatypes/hashmap.py
nanamilang/datatypes/hashset.py
nanamilang/datatypes/integernumber.py
nanamilang/datatypes/interop.py
nanamilang/datatypes/keyword.py
nanamilang/datatypes/macro.py
nanamilang/datatypes/nexception.py
nanamilang/datatypes/nil.py
nanamilang/datatypes/numeric.py
nanamilang/datatypes/string.py
nanamilang/datatypes/symbol.py
nanamilang/datatypes/type.py
nanamilang/datatypes/undefined.py
nanamilang/datatypes/vector.py
nanamilang-0.43.2.data/scripts/nanamilang-eval.py
nanamilang-0.43.2.data/scripts/nanamilang-repl.py
nanamilang-0.43.2.dist-info/LICENSE
nanamilang-0.43.2.dist-info/METADATA
nanamilang-0.43.2.dist-info/WHEEL
nanamilang-0.43.2.dist-info/top_level.txt
nanamilang-0.43.2.dist-info/RECORD
